{
    "Afghanistan": {
        "capital": "Kabul",
        "definiteArticle": false
    },
    "Armenia": {
        "capital": "Yerevan",
        "definiteArticle": false
    },
    "Azerbaijan": {
        "capital": "Baku",
        "definiteArticle": false
    },
    "Bahrain": {
        "capital": "Manama",
        "definiteArticle": false
    },
    "Bangladesh": {
        "capital": "Dhaka",
        "definiteArticle": false
    },
    "Bhutan": {
        "capital": "Thimphu",
        "definiteArticle": false
    },
    "Brunei": {
        "capital": "Bandar Seri Begawan",
        "definiteArticle": false
    },
    "Cambodia": {
        "capital": "Phnom Penh",
        "definiteArticle": false
    },
    "China": {
        "capital": "Beijing",
        "definiteArticle": false
    },
    "Cyprus": {
        "capital": "Nicosia",
        "definiteArticle": false
    },
    "Georgia": {
        "capital": "Tbilisi",
        "definiteArticle": false
    },
    "India": {
        "capital": "New Delhi",
        "definiteArticle": false
    },
    "Indonesia": {
        "capital": "Jakarta",
        "definiteArticle": false
    },
    "Iran": {
        "capital": "Tehran",
        "definiteArticle": false
    },
    "Iraq": {
        "capital": "Baghdad",
        "definiteArticle": false
    },
    "Israel": {
        "capital": "Jerusalem",
        "definiteArticle": false
    },
    "Japan": {
        "capital": "Tokyo",
        "definiteArticle": false
    },
    "Jordan": {
        "capital": "Amman",
        "definiteArticle": false
    },
    "Kazakhstan": {
        "capital": "Astana",
        "definiteArticle": false
    },
    "Kuwait": {
        "capital": "Kuwait City",
        "definiteArticle": false
    },
    "Kyrgyzstan": {
        "capital": "Bishkek",
        "definiteArticle": false
    },
    "Laos": {
        "capital": "Vientiane",
        "definiteArticle": false
    },
    "Lebanon": {
        "capital": "Beirut",
        "definiteArticle": false
    },
    "Malaysia": {
        "capital": "Kuala Lumpur",
        "definiteArticle": false
    },
    "Maldives": {
        "capital": "Malé",
        "definiteArticle": false
    },
    "Mongolia": {
        "capital": "Ulaanbaatar",
        "definiteArticle": false
    },
    "Myanmar": {
        "capital": "Naypyidaw",
        "definiteArticle": false
    },
    "Nepal": {
        "capital": "Kathmandu",
        "definiteArticle": false
    },
    "North Korea": {
        "capital": "Pyongyang",
        "definiteArticle": false
    },
    "Oman": {
        "capital": "Muscat",
        "definiteArticle": false
    },
    "Pakistan": {
        "capital": "Islamabad",
        "definiteArticle": false
    },
    "Palestine": {
        "capital": "East Jerusalem",
        "definiteArticle": false
    },
    "Philippines": {
        "capital": "Manila",
        "definiteArticle": true
    },
    "Qatar": {
        "capital": "Doha",
        "definiteArticle": false
    },
    "Russia": {
        "capital": "Moscow",
        "definiteArticle": false
    },
    "Saudi Arabia": {
        "capital": "Riyadh",
        "definiteArticle": false
    },
    "Singapore": {
        "capital": "Singapore",
        "definiteArticle": false
    },
    "South Korea": {
        "capital": "Seoul",
        "definiteArticle": false
    },
    "Sri Lanka": {
        "capital": "Sri Jayawardenepura Kotte",
        "definiteArticle": false
    },
    "Syria": {
        "capital": "Damascus",
        "definiteArticle": false
    },
    "Taiwan": {
        "capital": "Taipei",
        "definiteArticle": false
    },
    "Tajikistan": {
        "capital": "Dushanbe",
        "definiteArticle": false
    },
    "Thailand": {
        "capital": "Bangkok",
        "definiteArticle": false
    },
    "Timor-Leste": {
        "capital": "Dili",
        "definiteArticle": false
    },
    "Turkey": {
        "capital": "Ankara",
        "definiteArticle": false
    },
    "Turkmenistan": {
        "capital": "Ashgabat",
        "definiteArticle": false
    },
    "United Arab Emirates": {
        "capital": "Abu Dhabi",
        "definiteArticle": false
    },
    "Uzbekistan": {
        "capital": "Tashkent",
        "definiteArticle": false
    },
    "Vietnam": {
        "capital": "Hanoi",
        "definiteArticle": false
    },
    "Yemen": {
        "capital": "Sana'a",
        "definiteArticle": false
    }
}
